ben42code/myitertools/__init__.py
ben42code/myitertools/islice_extended.py
ben42code_myitertools-0.0.5.dist-info/licenses/LICENSE
ben42code_myitertools-0.0.5.dist-info/WHEEL
ben42code_myitertools-0.0.5.dist-info/METADATA
ben42code_myitertools-0.0.5.dist-info/RECORD
