Metadata-Version: 2.4
Name: ben42code.myitertools
Version: 0.0.5
Summary: Providing some additional capabilities on top of itertools.
Author-email: ben42code+myitertools@gmail.com
Requires-Python: >=3.9
License-Expression: MIT
Classifier: Development Status :: 3 - Alpha
Classifier: Programming Language :: Python :: 3
Classifier: Operating System :: OS Independent
License-File: LICENSE
Project-URL: Homepage, https://github.com/ben42code/myitertools
